{">0":{"n":"console","c":{">0":{"n":"libs","c":{">0":{"n":"tasks","c":{"bake_task":"bake.php","controller_task":"controller.php","db_config_task":"db_config.php","extract_task":"extract.php","fixture_task":"fixture.php","model_task":"model.php","plugin_task":"plugin.php","project_task":"project.php","template_task":"template.php","test_task":"test.php","view_task":"view.php"}},"shell":"shell.php","acl_shell":"acl.php","api_shell":"api.php","bake_shell":"bake.php","console_shell":"console.php","i18n_shell":"i18n.php","schema_shell":"schema.php","test_suite_shell":"testsuite.php"}},"shell_dispatcher":"cake.php"}},">1":{"n":"libs","c":{">0":{"n":"controller","c":{">0":{"n":"components","c":{"acl_component":"acl.php","auth_component":"auth.php","cookie_component":"cookie.php","email_component":"email.php","request_handler_component":"request_handler.php","security_component":"security.php","session_component":"session.php"}},"app_controller":"","component":"","controller":"","pages_controller":"","scaffold":""}},">1":{"n":"log","c":{"file_log":""}},">2":{"n":"model","c":{">0":{"n":"behaviors","c":{"acl_behavior":"acl.php","containable_behavior":"containable.php","translate_behavior":"translate.php","tree_behavior":"tree.php"}},">1":{"n":"datasources","c":{">0":{"n":"dbo","c":{"dbo_mssql":"","dbo_mysql":"","dbo_mysqli":"","dbo_oracle":"","dbo_postgres":"","dbo_sqlite":""}},"datasource":"","dbo_source":""}},"app_model":"","cake_schema":"","connection_manager":"","model":"","model_behavior":"","acl_node":"db_acl.php","aco":"db_acl.php","aco_action":"db_acl.php","aro":"db_acl.php","permission":"db_acl.php"}},">3":{"n":"view","c":{">0":{"n":"helpers","c":{"app_helper":"","ajax_helper":"ajax.php","cache_helper":"cache.php","form_helper":"form.php","html_helper":"html.php","javascript_helper":"javascript.php","jquery_engine_helper":"jquery_engine.php","js_helper":"js.php","mootools_engine_helper":"mootools_engine.php","number_helper":"number.php","paginator_helper":"paginator.php","prototype_engine_helper":"prototype_engine.php","rss_helper":"rss.php","session_helper":"session.php","text_helper":"text.php","time_helper":"time.php","xml_helper":"xml.php"}},"helper":"","view":"","media_view":"media.php","theme_view":"theme.php"}},"cache":"","cake_log":"","cake_session":"","cake_socket":"","class_registry":"","configure":"","debugger":"","file":"","folder":"","http_socket":"","i18n":"","inflector":"","l10n":"","magic_db":"","multibyte":"","object":"","router":"","sanitize":"","security":"","set":"","string":"","validation":"","cake_error_controller":"error.php","error_handler":"error.php","overloadable":"overloadable_php5.php","xml_node":"xml.php","xml":"xml.php","xml_element":"xml.php","xml_text_node":"xml.php","xml_manager":"xml.php"}},">2":{"n":"tests","c":{">0":{"n":"cases","c":{">0":{"n":"console","c":{">0":{"n":"libs","c":{">0":{"n":"tasks","c":{"controller_task_test":"controller.test.php","db_config_task_test":"db_config.test.php","extract_task_test":"extract.test.php","fixture_task_test":"fixture.test.php","model_task_test":"model.test.php","plugin_task_test":"plugin.test.php","project_task_test":"project.test.php","template_task_test":"template.test.php","test_task_test":"test.test.php","view_task_test":"view.test.php"}},"acl_shell_test":"acl.test.php","api_shell_test":"api.test.php","bake_shell_test_case":"bake.test.php","schema_shell_test_schema":"schema.test.php","schema_shell_test":"schema.test.php","test_shell":"shell.test.php","shell_test":"shell.test.php"}},"test_shell_dispatcher":"cake.test.php","shell_dispatcher_test":"cake.test.php"}},">1":{"n":"libs","c":{">0":{"n":"cache","c":{"apc_engine_test":"apc.test.php","file_engine_test":"file.test.php","memcache_engine_test":"memcache.test.php","xcache_engine_test":"xcache.test.php"}},">1":{"n":"controller","c":{">0":{"n":"components","c":{"acl_component_test":"acl.test.php","auth_test":"auth.test.php","test_auth_component":"auth.test.php","cookie_component_test":"cookie.test.php","email_component_test":"email.test.php","request_handler_component_test":"request_handler.test.php","security_component_test":"security.test.php","session_component_test":"session.test.php"}},"component_test":"component.test.php","controller_test":"controller.test.php","pages_controller_test":"pages_controller.test.php","scaffold_test":"scaffold.test.php","controller_merge_vars_test_case":"controller_merge_vars.test.php"}},">2":{"n":"log","c":{"file_log_test":"file_log.test.php"}},">3":{"n":"model","c":{">0":{"n":"behaviors","c":{"acl_behavior_test_case":"acl.test.php","containable_behavior_test":"containable.test.php","translate_behavior_test":"translate.test.php","number_tree_test":"tree.test.php"}},">1":{"n":"datasources","c":{">0":{"n":"dbo","c":{"dbo_mssql_test":"dbo_mssql.test.php","dbo_mysql_test":"dbo_mysql.test.php","dbo_mysqli_test":"dbo_mysqli.test.php","dbo_oracle_test":"dbo_oracle.test.php","dbo_postgres_test":"dbo_postgres.test.php","dbo_sqlite_test":"dbo_sqlite.test.php"}},"dbo_source_test":"dbo_source.test.php"}},"cake_schema_test":"cake_schema.test.php","connection_manager_test":"connection_manager.test.php","db_acl_test":"db_acl.test.php","model_delete_test":"model_delete.test.php","model_integration_test":"model_integration.test.php","model_read_test":"model_read.test.php","model_validation_test":"model_validation.test.php","model_write_test":"model_write.test.php","base_model_test":"model.test.php","behavior_test":"model_behavior.test.php"}},">4":{"n":"view","c":{">0":{"n":"helpers","c":{"ajax_helper_test":"ajax.test.php","cache_helper_test":"cache.test.php","form_helper_test":"form.test.php","html_helper_test":"html.test.php","javascript_test":"javascript.test.php","jquery_engine_helper_test_case":"jquery_engine.test.php","js_helper_test_case":"js.test.php","moo_engine_helper_test_case":"mootools_engine.test.php","number_helper_test":"number.test.php","paginator_helper_test":"paginator.test.php","prototype_engine_helper_test_case":"prototype_engine.test.php","rss_helper_test":"rss.test.php","session_helper_test":"session.test.php","text_helper_test":"text.test.php","time_helper_test":"time.test.php","xml_helper_test":"xml.test.php"}},"helper_test":"helper.test.php","view_test":"view.test.php","media_view_test":"media.test.php","theme_view_test":"theme.test.php"}},"cache_test":"cache.test.php","cake_log_test":"cake_log.test.php","cake_session_test":"cake_session.test.php","cake_socket_test":"cake_socket.test.php","cake_test_case_test":"cake_test_case.test.php","cake_test_fixture_test":"cake_test_fixture.test.php","class_registry_test":"class_registry.test.php","code_coverage_manager_test":"code_coverage_manager.test.php","configure_test":"configure.test.php","debugger_test":"debugger.test.php","error_test":"error.test.php","file_test":"file.test.php","folder_test":"folder.test.php","http_socket_test":"http_socket.test.php","i18n_test":"i18n.test.php","inflector_test":"inflector.test.php","l10n_test":"l10n.test.php","magic_db_test":"magic_db.test.php","multibyte_test":"multibyte.test.php","object_test":"object.test.php","overloadable_test":"overloadable.test.php","router_test":"router.test.php","sanitize_test":"sanitize.test.php","security_test":"security.test.php","set_test":"set.test.php","string_test":"string.test.php","test_manager_test":"test_manager.test.php","validation_test":"validation.test.php","xml_test":"xml.test.php"}},"basics_test":"basics.test.php","dispatcher_test":"dispatcher.test.php"}},">1":{"n":"lib","c":{">0":{"n":"reporter","c":{"cake_base_reporter":"","cake_cli_reporter":"","cake_html_reporter":"","cake_text_reporter":""}},"cake_test_case":"","cake_test_fixture":"","cake_test_model":"","cake_test_suite_dispatcher":"","cake_web_test_case":"","code_coverage_manager":"","test_manager":"","cake_test_dispatcher":"cake_test_case.php"}}}},"dispatcher":""}